muji/__init__.py
muji/interpreter.py
muji/lexer.py
muji/main.py
muji/mukhya.py
muji/parser.py
muji/token_types.py
muji_bhasa-1.1.4.dist-info/METADATA
muji_bhasa-1.1.4.dist-info/WHEEL
muji_bhasa-1.1.4.dist-info/entry_points.txt
muji_bhasa-1.1.4.dist-info/top_level.txt
muji_bhasa-1.1.4.dist-info/RECORD
